{
    "CodigoInterno":227584,
    "Identificacion":"Documento oficial que acredita el nacimiento de una persona, necesario para trámites de identidad y registro civil",
    "Tramite":"certificado de nacimiento",
    "Variables": [
	{
	    "Caption":"¿Tenés turno asignado?",
	    "Codigo":"30",
	    "Pedir":"Si",
	    "PorDefecto":"",
	    "Tipo":"booleano",
	    "Valor":"",
	    "Vector":"No"
	},
	{
	    "Caption":"¿Contás con el acta de nacimiento?",
	    "Codigo":"31",
	    "Pedir":"Si",
	    "PorDefecto":"",
	    "Tipo":"booleano",
	    "Valor":"",
	    "Vector":"No"
	},
	{
	    "Caption":"Nombre completo del recién nacido",
	    "Codigo":"32",
	    "Pedir":"Si",
	    "PorDefecto":"",
	    "Tipo":"texto",
	    "Valor":"",
	    "Vector":"No"
	},
	{
	    "Caption":"Profesión u ocupación",
	    "Codigo":"33",
	    "Pedir":"Si",
	    "PorDefecto":"",
	    "Tipo":"texto",
	    "Valor":"",
	    "Vector":"No"
	},
	{
	    "Caption":"Observaciones adicionales",
	    "Codigo":"34",
	    "Pedir":"Si",
	    "PorDefecto":"",
	    "Tipo":"texto",
	    "Valor":"",
	    "Vector":"No"
	},
	{
	    "Caption":"¿Realizaste el pago de las tasas?",
	    "Codigo":"35",
	    "Pedir":"Si",
	    "PorDefecto":"",
	    "Tipo":"booleano",
	    "Valor":"",
	    "Vector":"No"
	}
    ],
    "asincronico":false,
    "loginNecesario":0
}